LICENSE
graph_progression/__init__.py
graph_progression/generators.py
graph_progression/progressors.py
graph_progression/py.typed
graph_progression/selectors.py
graph_progression-0.0.2.dist-info/LICENSE
graph_progression-0.0.2.dist-info/WHEEL
graph_progression-0.0.2.dist-info/METADATA
graph_progression-0.0.2.dist-info/RECORD
