Metadata-Version: 2.1
Name: graph-progression
Version: 0.0.2
Summary: Create a progression of recommendations from a user-supplied recommender
Home-page: https://github.com/askarthur/graph-progression
License: MIT
Author: Marco Gancitano
Author-email: marco.gancitano@askarthur.art
Requires-Python: >=3.7,<4.0
Classifier: License :: OSI Approved :: MIT License
Classifier: Natural Language :: English
Classifier: Programming Language :: Python :: 3
Classifier: Programming Language :: Python :: 3.10
Classifier: Programming Language :: Python :: 3.7
Classifier: Programming Language :: Python :: 3.8
Classifier: Programming Language :: Python :: 3.9
Requires-Dist: importlib_metadata (>=3.4.0,<4.0.0)
